UART_imp.srcs/sources_1/new/uart_rx.v
module uart_rx (
    input wire clk,
    input wire rst,
    input wire rx,
    output reg [7:0] rx_data,
    output reg rx_done
);

parameter CLK_PER_BIT = 434;  // For 115200 baud with 50 MHz clock

localparam IDLE         = 3'b000;
localparam START_BIT    = 3'b001;
localparam DATA_BITS    = 3'b010;
localparam STOP_BIT     = 3'b011;
localparam CLEANUP      = 3'b100;

reg [2:0] state = IDLE;
reg [15:0] clk_count = 0;
reg [2:0] bit_index = 0;
reg [7:0] rx_shift = 0;

always @(posedge clk or posedge rst) begin
    if (rst) begin
        state <= IDLE;
        rx_data <= 8'b0;
        rx_done <= 0;
        clk_count <= 0;
        bit_index <= 0;
        rx_shift <= 0;
    end else begin
        case (state)
            IDLE: begin
                rx_done <= 0;
                clk_count <= 0;
                bit_index <= 0;

                if (rx == 0)  // Start bit detected
                    state <= START_BIT;
            end

            START_BIT: begin
                if (clk_count == (CLK_PER_BIT / 2)) begin
                    if (rx == 0) begin
                        clk_count <= 0;
                        state <= DATA_BITS;
                    end else begin
                        state <= IDLE;  // False start
                    end
                end else begin
                    clk_count <= clk_count + 1;
                end
            end

            DATA_BITS: begin
                if (clk_count == CLK_PER_BIT - 1) begin
                    clk_count <= 0;
                    rx_shift[bit_index] <= rx;

                    if (bit_index < 7)
                        bit_index <= bit_index + 1;
                    else begin
                        bit_index <= 0;
                        state <= STOP_BIT;
                    end
                end else begin
                    clk_count <= clk_count + 1;
                end
            end

            STOP_BIT: begin
                if (clk_count == CLK_PER_BIT - 1) begin
                    rx_data <= rx_shift;
                    rx_done <= 1;
                    clk_count <= 0;
                    state <= CLEANUP;
                end else begin
                    clk_count <= clk_count + 1;
                end
            end

            CLEANUP: begin
                state <= IDLE;
                rx_done <= 0;
            end

            default: state <= IDLE;
        endcase
    end
end

endmodule

UART_imp.srcs/sources_1/new/uart_tx.v
module uart_tx (
    input wire clk,
    input wire rst,
    input wire tx_start,
    input wire [7:0] tx_data,
    output reg tx,
    output reg tx_busy
);

parameter CLK_PER_BIT = 434;  // For 115200 baud with 50 MHz clock

reg [15:0] clk_count = 0;
reg [3:0] bit_index = 0;
reg [9:0] tx_shift = 10'b1111111111;
reg sending = 0;

always @(posedge clk or posedge rst) begin
    if (rst) begin
        tx <= 1;
        tx_busy <= 0;
        clk_count <= 0;
        bit_index <= 0;
        sending <= 0;
    end else begin
        if (tx_start && !tx_busy) begin
            tx_shift <= {1'b1, tx_data, 1'b0};  // stop, data, start
            sending <= 1;
            tx_busy <= 1;
            clk_count <= 0;
            bit_index <= 0;
        end else if (sending) begin
            if (clk_count == CLK_PER_BIT - 1) begin
                clk_count <= 0;
                tx <= tx_shift[bit_index];
                bit_index <= bit_index + 1;
                if (bit_index == 9) begin
                    sending <= 0;
                    tx_busy <= 0;
                    tx <= 1;
                end
            end else begin
                clk_count <= clk_count + 1;
            end
        end
    end
end

endmodule

UART_imp.srcs/sim_1/new/uart_tb.v
`timescale 1ns/1ps

module uart_tb;

// Clock and Reset
reg clk = 0;
reg rst = 1;

// TX interface
reg tx_start = 0;
reg [7:0] tx_data = 8'h00;
wire tx;
wire tx_busy;

// RX interface
wire [7:0] rx_data;
wire rx_done;

// Instantiate Transmitter
uart_tx #(
    .CLK_PER_BIT(434)  // 115200 baud @ 50 MHz
) uart_tx_inst (
    .clk(clk),
    .rst(rst),
    .tx_start(tx_start),
    .tx_data(tx_data),
    .tx(tx),
    .tx_busy(tx_busy)
);

// Instantiate Receiver
uart_rx #(
    .CLK_PER_BIT(434)
) uart_rx_inst (
    .clk(clk),
    .rst(rst),
    .rx(tx),  // loopback connection
    .rx_data(rx_data),
    .rx_done(rx_done)
);

// Clock generation (50 MHz)
always #10 clk = ~clk;

initial begin
    $dumpfile("uart_tb.vcd");
    $dumpvars(0, uart_tb);

    // Initial state
    rst = 1;
    #50;
    rst = 0;

    // Send first byte
    #100;
    tx_data = 8'hA5;
    tx_start = 1;
    #20 tx_start = 0;

    // Wait for transmission
    wait (rx_done == 1);
    #20;

    $display("Sent byte: 0x%02X, Received byte: 0x%02X", tx_data, rx_data);

    // Send second byte
    tx_data = 8'h3C;
    tx_start = 1;
    #20 tx_start = 0;

    wait (rx_done == 1);
    #20;

    $display("Sent byte: 0x%02X, Received byte: 0x%02X", tx_data, rx_data);

    #1000;
    $finish;
end

endmodule

UART_imp.sim/sim_1/behav/xsim/uart_tb.vcd
$date
   Fri Apr 18 21:54:49 2025
$end

$version
  2024.2.0
  $dumpfile ("uart_tb.vcd") 
$end

$timescale
  1ps
$end

$scope module uart_tb $end
$var reg 1 ! clk $end
$var reg 1 " rst $end
$var reg 1 # tx_start $end
$var reg 8 $ tx_data [7:0] $end
$var wire 1 % tx $end
$var wire 1 & tx_busy $end
$var wire 8 ' rx_data [7:0] $end
$var wire 1 ( rx_done $end
$scope module uart_tx_inst $end
$var wire 1 ) clk $end
$var wire 1 * rst $end
$var wire 1 + tx_start $end
$var wire 8 , tx_data [7:0] $end
$var reg 1 - tx $end
$var reg 1 . tx_busy $end
$var reg 16 / clk_count [15:0] $end
$var reg 4 0 bit_index [3:0] $end
$var reg 10 1 tx_shift [9:0] $end
$var reg 1 2 sending $end
$upscope $end
$scope module uart_rx_inst $end
$var wire 1 3 clk $end
$var wire 1 4 rst $end
$var wire 1 % rx $end
$var reg 8 5 rx_data [7:0] $end
$var reg 1 6 rx_done $end
$var reg 3 7 state [2:0] $end
$var reg 16 8 clk_count [15:0] $end
$var reg 3 9 bit_index [2:0] $end
$var reg 8 : rx_shift [7:0] $end
$upscope $end
$upscope $end
$enddefinitions $end

#0
$dumpvars
0!
1"
0#
b0 $
1%
0&
b0 '
0(
0)
1*
0+
b0 ,
1-
0.
b0 /
b0 0
b1111111111 1
02
03
14
b0 5
06
b0 7
b0 8
b0 9
b0 :
$end

#10000
1!
1)
13

#20000
0!
0)
03

#30000
1!
1)
13

#40000
0!
0)
03

#50000
1!
0"
1)
0*
13
04

#60000
0!
0)
03

#70000
1!
1)
13

#80000
0!
0)
03

#90000
1!
1)
13

#100000
0!
0)
03

#110000
1!
1)
13

#120000
0!
0)
03

#130000
1!
1)
13

#140000
0!
0)
03

#150000
1!
1#
b10100101 $
1&
1)
1+
b10100101 ,
1.
b1101001010 1
12
13

#160000
0!
0)
03

#170000
1!
0#
1)
0+
b1 /
13

#180000
0!
0)
03

#190000
1!
1)
b10 /
13

#200000
0!
0)
03

#210000
1!
1)
b11 /
13

#220000
0!
0)
03

#230000
1!
1)
b100 /
13

#240000
0!
0)
03

#250000
1!
1)
b101 /
13

#260000
0!
0)
03

#270000
1!
1)
b110 /
13

#280000
0!
0)
03

#290000
1!
1)
b111 /
13

#300000
0!
0)
03

#310000
1!
1)
b1000 /
13

#320000
0!
0)
03

#330000
1!
1)
b1001 /
13

#340000
0!
0)
03

#350000
1!
1)
b1010 /
13

#360000
0!
0)
03

#370000
1!
1)
b1011 /
13

#380000
0!
0)
03

#390000
1!
1)
b1100 /
13

#400000
0!
0)
03

#410000
1!
1)
b1101 /
13

#420000
0!
0)
03

#430000
1!
1)
b1110 /
13

#440000
0!
0)
03

#450000
1!
1)
b1111 /
13

#460000
0!
0)
03

#470000
1!
1)
b10000 /
13

#480000
0!
0)
03

#490000
1!
1)
b10001 /
13

#500000
0!
0)
03

#510000
1!
1)
b10010 /
13

#520000
0!
0)
03

#530000
1!
1)
b10011 /
13

#540000
0!
0)
03

#550000
1!
1)
b10100 /
13

#560000
0!
0)
03

#570000
1!
1)
b10101 /
13

#580000
0!
0)
03

#590000
1!
1)
b10110 /
13

#600000
0!
0)
03

#610000
1!
1)
b10111 /
13

#620000
0!
0)
03

#630000
1!
1)
b11000 /
13

#640000
0!
0)
03

#650000
1!
1)
b11001 /
13

#660000
0!
0)
03

#670000
1!
1)
b11010 /
13

#680000
0!
0)
03

#690000
1!
1)
b11011 /
13

#700000
0!
0)
03

#710000
1!
1)
b11100 /
13

#720000
0!
0)
03

#730000
1!
1)
b11101 /
13

#740000
0!
0)
03

#750000
1!
1)
b11110 /
13

#760000
0!
0)
03

#770000
1!
1)
b11111 /
13

#780000
0!
0)
03

#790000
1!
1)
b100000 /
13

#800000
0!
0)
03

#810000
1!
1)
b100001 /
13

#820000
0!
0)
03

#830000
1!
1)
b100010 /
13

#840000
0!
0)
03

#850000
1!
1)
b100011 /
13

#860000
0!
0)
03

#870000
1!
1)
b100100 /
13

#880000
0!
0)
03

#890000
1!
1)
b100101 /
13

#900000
0!
0)
03

#910000
1!
1)
b100110 /
13

#920000
0!
0)
03

#930000
1!
1)
b100111 /
13

#940000
0!
0)
03

#950000
1!
1)
b101000 /
13

#960000
0!
0)
03

#970000
1!
1)
b101001 /
13

#980000
0!
0)
03

#990000
1!
1)
b101010 /
13

#1000000
0!
0)
03

#1010000
1!
1)
b101011 /
13

#1020000
0!
0)
03

#1030000
1!
1)
b101100 /
13

#1040000
0!
0)
03

#1050000
1!
1)
b101101 /
13

#1060000
0!
0)
03

#1070000
1!
1)
b101110 /
13

#1080000
0!
0)
03

#1090000
1!
1)
b101111 /
13

#1100000
0!
0)
03

#1110000
1!
1)
b110000 /
13

#1120000
0!
0)
03

#1130000
1!
1)
b110001 /
13

#1140000
0!
0)
03

#1150000
1!
1)
b110010 /
13

#1160000
0!
0)
03

#1170000
1!
1)
b110011 /
13

#1180000
0!
0)
03

#1190000
1!
1)
b110100 /
13

#1200000
0!
0)
03

#1210000
1!
1)
b110101 /
13

#1220000
0!
0)
03

#1230000
1!
1)
b110110 /
13

#1240000
0!
0)
03

#1250000
1!
1)
b110111 /
13

#1260000
0!
0)
03

#1270000
1!
1)
b111000 /
13

#1280000
0!
0)
03

#1290000
1!
1)
b111001 /
13

#1300000
0!
0)
03

#1310000
1!
1)
b111010 /
13

#1320000
0!
0)
03

#1330000
1!
1)
b111011 /
13

#1340000
0!
0)
03

#1350000
1!
1)
b111100 /
13

#1360000
0!
0)
03

#1370000
1!
1)
b111101 /
13

#1380000
0!
0)
03

#1390000
1!
1)
b111110 /
13

#1400000
0!
0)
03

#1410000
1!
1)
b111111 /
13

#1420000
0!
0)
03

#1430000
1!
1)
b1000000 /
13

#1440000
0!
0)
03

#1450000
1!
1)
b1000001 /
13

#1460000
0!
0)
03

#1470000
1!
1)
b1000010 /
13

#1480000
0!
0)
03

#1490000
1!
1)
b1000011 /
13

#1500000
0!
0)
03

#1510000
1!
1)
b1000100 /
13

#1520000
0!
0)
03

#1530000
1!
1)
b1000101 /
13

#1540000
0!
0)
03

#1550000
1!
1)
b1000110 /
13

#1560000
0!
0)
03

#1570000
1!
1)
b1000111 /
13

#1580000
0!
0)
03

#1590000
1!
1)
b1001000 /
13

#1600000
0!
0)
03

#1610000
1!
1)
b1001001 /
13

#1620000
0!
0)
03

#1630000
1!
1)
b1001010 /
13

#1640000
0!
0)
03

#1650000
1!
1)
b1001011 /
13

#1660000
0!
0)
03

#1670000
1!
1)
b1001100 /
13

#1680000
0!
0)
03

#1690000
1!
1)
b1001101 /
13

#1700000
0!
0)
03

#1710000
1!
1)
b1001110 /
13

#1720000
0!
0)
03

#1730000
1!
1)
b1001111 /
13

#1740000
0!
0)
03

#1750000
1!
1)
b1010000 /
13

#1760000
0!
0)
03

#1770000
1!
1)
b1010001 /
13

#1780000
0!
0)
03

#1790000
1!
1)
b1010010 /
13

#1800000
0!
0)
03

#1810000
1!
1)
b1010011 /
13

#1820000
0!
0)
03

#1830000
1!
1)
b1010100 /
13

#1840000
0!
0)
03

#1850000
1!
1)
b1010101 /
13

#1860000
0!
0)
03

#1870000
1!
1)
b1010110 /
13

#1880000
0!
0)
03

#1890000
1!
1)
b1010111 /
13

#1900000
0!
0)
03

#1910000
1!
1)
b1011000 /
13

#1920000
0!
0)
03

#1930000
1!
1)
b1011001 /
13

#1940000
0!
0)
03

#1950000
1!
1)
b1011010 /
13

#1960000
0!
0)
03

#1970000
1!
1)
b1011011 /
13

#1980000
0!
0)
03

#1990000
1!
1)
b1011100 /
13

#2000000
0!
0)
03

#2010000
1!
1)
b1011101 /
13

#2020000
0!
0)
03

#2030000
1!
1)
b1011110 /
13

#2040000
0!
0)
03

#2050000
1!
1)
b1011111 /
13

#2060000
0!
0)
03

#2070000
1!
1)
b1100000 /
13

#2080000
0!
0)
03

#2090000
1!
1)
b1100001 /
13

#2100000
0!
0)
03

#2110000
1!
1)
b1100010 /
13

#2120000
0!
0)
03

#2130000
1!
1)
b1100011 /
13

#2140000
0!
0)
03

#2150000
1!
1)
b1100100 /
13

#2160000
0!
0)
03

#2170000
1!
1)
b1100101 /
13

#2180000
0!
0)
03

#2190000
1!
1)
b1100110 /
13

#2200000
0!
0)
03

#2210000
1!
1)
b1100111 /
13

#2220000
0!
0)
03

#2230000
1!
1)
b1101000 /
13

#2240000
0!
0)
03

#2250000
1!
1)
b1101001 /
13

#2260000
0!
0)
03

#2270000
1!
1)
b1101010 /
13

#2280000
0!
0)
03

#2290000
1!
1)
b1101011 /
13

#2300000
0!
0)
03

#2310000
1!
1)
b1101100 /
13

#2320000
0!
0)
03

#2330000
1!
1)
b1101101 /
13

#2340000
0!
0)
03

#2350000
1!
1)
b1101110 /
13

#2360000
0!
0)
03

#2370000
1!
1)
b1101111 /
13

#2380000
0!
0)
03

#2390000
1!
1)
b1110000 /
13

#2400000
0!
0)
03

#2410000
1!
1)
b1110001 /
13

#2420000
0!
0)
03

#2430000
1!
1)
b1110010 /
13

#2440000
0!
0)
03

#2450000
1!
1)
b1110011 /
13

#2460000
0!
0)
03

#2470000
1!
1)
b1110100 /
13

#2480000
0!
0)
03

#2490000
1!
1)
b1110101 /
13

#2500000
0!
0)
03

#2510000
1!
1)
b1110110 /
13

#2520000
0!
0)
03

#2530000
1!
1)
b1110111 /
13

#2540000
0!
0)
03

#2550000
1!
1)
b1111000 /
13

#2560000
0!
0)
03

#2570000
1!
1)
b1111001 /
13

#2580000
0!
0)
03

#2590000
1!
1)
b1111010 /
13

#2600000
0!
0)
03

#2610000
1!
1)
b1111011 /
13

#2620000
0!
0)
03

#2630000
1!
1)
b1111100 /
13

#2640000
0!
0)
03

#2650000
1!
1)
b1111101 /
13

#2660000
0!
0)
03

#2670000
1!
1)
b1111110 /
13

#2680000
0!
0)
03

#2690000
1!
1)
b1111111 /
13

#2700000
0!
0)
03

#2710000
1!
1)
b10000000 /
13

#2720000
0!
0)
03

#2730000
1!
1)
b10000001 /
13

#2740000
0!
0)
03

#2750000
1!
1)
b10000010 /
13

#2760000
0!
0)
03

#2770000
1!
1)
b10000011 /
13

#2780000
0!
0)
03

#2790000
1!
1)
b10000100 /
13

#2800000
0!
0)
03

#2810000
1!
1)
b10000101 /
13

#2820000
0!
0)
03

#2830000
1!
1)
b10000110 /
13

#2840000
0!
0)
03

#2850000
1!
1)
b10000111 /
13

#2860000
0!
0)
03

#2870000
1!
1)
b10001000 /
13

#2880000
0!
0)
03

#2890000
1!
1)
b10001001 /
13

#2900000
0!
0)
03

#2910000
1!
1)
b10001010 /
13

#2920000
0!
0)
03

#2930000
1!
1)
b10001011 /
13

#2940000
0!
0)
03

#2950000
1!
1)
b10001100 /
13

#2960000
0!
0)
03

#2970000
1!
1)
b10001101 /
13

#2980000
0!
0)
03

#2990000
1!
1)
b10001110 /
13

#3000000
0!
0)
03

#3010000
1!
1)
b10001111 /
13

#3020000
0!
0)
03

#3030000
1!
1)
b10010000 /
13

#3040000
0!
0)
03

#3050000
1!
1)
b10010001 /
13

#3060000
0!
0)
03

#3070000
1!
1)
b10010010 /
13

#3080000
0!
0)
03

#3090000
1!
1)
b10010011 /
13

#3100000
0!
0)
03

#3110000
1!
1)
b10010100 /
13

#3120000
0!
0)
03

#3130000
1!
1)
b10010101 /
13

#3140000
0!
0)
03

#3150000
1!
1)
b10010110 /
13

#3160000
0!
0)
03

#3170000
1!
1)
b10010111 /
13

#3180000
0!
0)
03

#3190000
1!
1)
b10011000 /
13

#3200000
0!
0)
03

#3210000
1!
1)
b10011001 /
13

#3220000
0!
0)
03

#3230000
1!
1)
b10011010 /
13

#3240000
0!
0)
03

#3250000
1!
1)
b10011011 /
13

#3260000
0!
0)
03

#3270000
1!
1)
b10011100 /
13

#3280000
0!
0)
03

#3290000
1!
1)
b10011101 /
13

#3300000
0!
0)
03

#3310000
1!
1)
b10011110 /
13

#3320000
0!
0)
03

#3330000
1!
1)
b10011111 /
13

#3340000
0!
0)
03

#3350000
1!
1)
b10100000 /
13

#3360000
0!
0)
03

#3370000
1!
1)
b10100001 /
13

#3380000
0!
0)
03

#3390000
1!
1)
b10100010 /
13

#3400000
0!
0)
03

#3410000
1!
1)
b10100011 /
13

#3420000
0!
0)
03

#3430000
1!
1)
b10100100 /
13

#3440000
0!
0)
03

#3450000
1!
1)
b10100101 /
13

#3460000
0!
0)
03

#3470000
1!
1)
b10100110 /
13

#3480000
0!
0)
03

#3490000
1!
1)
b10100111 /
13

#3500000
0!
0)
03

#3510000
1!
1)
b10101000 /
13

#3520000
0!
0)
03

#3530000
1!
1)
b10101001 /
13

#3540000
0!
0)
03

#3550000
1!
1)
b10101010 /
13

#3560000
0!
0)
03

#3570000
1!
1)
b10101011 /
13

#3580000
0!
0)
03

#3590000
1!
1)
b10101100 /
13

#3600000
0!
0)
03

#3610000
1!
1)
b10101101 /
13

#3620000
0!
0)
03

#3630000
1!
1)
b10101110 /
13

#3640000
0!
0)
03

#3650000
1!
1)
b10101111 /
13

#3660000
0!
0)
03

#3670000
1!
1)
b10110000 /
13

#3680000
0!
0)
03

#3690000
1!
1)
b10110001 /
13

#3700000
0!
0)
03

#3710000
1!
1)
b10110010 /
13

#3720000
0!
0)
03

#3730000
1!
1)
b10110011 /
13

#3740000
0!
0)
03

#3750000
1!
1)
b10110100 /
13

#3760000
0!
0)
03

#3770000
1!
1)
b10110101 /
13

#3780000
0!
0)
03

#3790000
1!
1)
b10110110 /
13

#3800000
0!
0)
03

#3810000
1!
1)
b10110111 /
13

#3820000
0!
0)
03

#3830000
1!
1)
b10111000 /
13

#3840000
0!
0)
03

#3850000
1!
1)
b10111001 /
13

#3860000
0!
0)
03

#3870000
1!
1)
b10111010 /
13

#3880000
0!
0)
03

#3890000
1!
1)
b10111011 /
13

#3900000
0!
0)
03

#3910000
1!
1)
b10111100 /
13

#3920000
0!
0)
03

#3930000
1!
1)
b10111101 /
13

#3940000
0!
0)
03

#3950000
1!
1)
b10111110 /
13

#3960000
0!
0)
03

#3970000
1!
1)
b10111111 /
13

#3980000
0!
0)
03

#3990000
1!
1)
b11000000 /
13

#4000000
0!
0)
03

#4010000
1!
1)
b11000001 /
13

#4020000
0!
0)
03

#4030000
1!
1)
b11000010 /
13

#4040000
0!
0)
03

#4050000
1!
1)
b11000011 /
13

#4060000
0!
0)
03

#4070000
1!
1)
b11000100 /
13

#4080000
0!
0)
03

#4090000
1!
1)
b11000101 /
13

#4100000
0!
0)
03

#4110000
1!
1)
b11000110 /
13

#4120000
0!
0)
03

#4130000
1!
1)
b11000111 /
13

#4140000
0!
0)
03

#4150000
1!
1)
b11001000 /
13

#4160000
0!
0)
03

#4170000
1!
1)
b11001001 /
13

#4180000
0!
0)
03

#4190000
1!
1)
b11001010 /
13

#4200000
0!
0)
03

#4210000
1!
1)
b11001011 /
13

#4220000
0!
0)
03

#4230000
1!
1)
b11001100 /
13

#4240000
0!
0)
03

#4250000
1!
1)
b11001101 /
13

#4260000
0!
0)
03

#4270000
1!
1)
b11001110 /
13

#4280000
0!
0)
03

#4290000
1!
1)
b11001111 /
13

#4300000
0!
0)
03

#4310000
1!
1)
b11010000 /
13

#4320000
0!
0)
03

#4330000
1!
1)
b11010001 /
13

#4340000
0!
0)
03

#4350000
1!
1)
b11010010 /
13

#4360000
0!
0)
03

#4370000
1!
1)
b11010011 /
13

#4380000
0!
0)
03

#4390000
1!
1)
b11010100 /
13

#4400000
0!
0)
03

#4410000
1!
1)
b11010101 /
13

#4420000
0!
0)
03

#4430000
1!
1)
b11010110 /
13

#4440000
0!
0)
03

#4450000
1!
1)
b11010111 /
13

#4460000
0!
0)
03

#4470000
1!
1)
b11011000 /
13

#4480000
0!
0)
03

#4490000
1!
1)
b11011001 /
13

#4500000
0!
0)
03

#4510000
1!
1)
b11011010 /
13

#4520000
0!
0)
03

#4530000
1!
1)
b11011011 /
13

#4540000
0!
0)
03

#4550000
1!
1)
b11011100 /
13

#4560000
0!
0)
03

#4570000
1!
1)
b11011101 /
13

#4580000
0!
0)
03

#4590000
1!
1)
b11011110 /
13

#4600000
0!
0)
03

#4610000
1!
1)
b11011111 /
13

#4620000
0!
0)
03

#4630000
1!
1)
b11100000 /
13

#4640000
0!
0)
03

#4650000
1!
1)
b11100001 /
13

#4660000
0!
0)
03

#4670000
1!
1)
b11100010 /
13

#4680000
0!
0)
03

#4690000
1!
1)
b11100011 /
13

#4700000
0!
0)
03

#4710000
1!
1)
b11100100 /
13

#4720000
0!
0)
03

#4730000
1!
1)
b11100101 /
13

#4740000
0!
0)
03

#4750000
1!
1)
b11100110 /
13

#4760000
0!
0)
03

#4770000
1!
1)
b11100111 /
13

#4780000
0!
0)
03

#4790000
1!
1)
b11101000 /
13

#4800000
0!
0)
03

#4810000
1!
1)
b11101001 /
13

#4820000
0!
0)
03

#4830000
1!
1)
b11101010 /
13

#4840000
0!
0)
03

#4850000
1!
1)
b11101011 /
13

#4860000
0!
0)
03

#4870000
1!
1)
b11101100 /
13

#4880000
0!
0)
03

#4890000
1!
1)
b11101101 /
13

#4900000
0!
0)
03

#4910000
1!
1)
b11101110 /
13

#4920000
0!
0)
03

#4930000
1!
1)
b11101111 /
13

#4940000
0!
0)
03

#4950000
1!
1)
b11110000 /
13

#4960000
0!
0)
03

#4970000
1!
1)
b11110001 /
13

#4980000
0!
0)
03

#4990000
1!
1)
b11110010 /
13

#5000000
0!
0)
03

#5010000
1!
1)
b11110011 /
13

#5020000
0!
0)
03

#5030000
1!
1)
b11110100 /
13

#5040000
0!
0)
03

#5050000
1!
1)
b11110101 /
13

#5060000
0!
0)
03

#5070000
1!
1)
b11110110 /
13

#5080000
0!
0)
03

#5090000
1!
1)
b11110111 /
13

#5100000
0!
0)
03

#5110000
1!
1)
b11111000 /
13

#5120000
0!
0)
03

#5130000
1!
1)
b11111001 /
13

#5140000
0!
0)
03

#5150000
1!
1)
b11111010 /
13

#5160000
0!
0)
03

#5170000
1!
1)
b11111011 /
13

#5180000
0!
0)
03

#5190000
1!
1)
b11111100 /
13

#5200000
0!
0)
03

#5210000
1!
1)
b11111101 /
13

#5220000
0!
0)
03

#5230000
1!
1)
b11111110 /
13

#5240000
0!
0)
03

#5250000
1!
1)
b11111111 /
13

#5260000
0!
0)
03

#5270000
1!
1)
b100000000 /
13

#5280000
0!
0)
03

#5290000
1!
1)
b100000001 /
13

#5300000
0!
0)
03

#5310000
1!
1)
b100000010 /
13

#5320000
0!
0)
03

#5330000
1!
1)
b100000011 /
13

#5340000
0!
0)
03

#5350000
1!
1)
b100000100 /
13

#5360000
0!
0)
03

#5370000
1!
1)
b100000101 /
13

#5380000
0!
0)
03

#5390000
1!
1)
b100000110 /
13

#5400000
0!
0)
03

#5410000
1!
1)
b100000111 /
13

#5420000
0!
0)
03

#5430000
1!
1)
b100001000 /
13

#5440000
0!
0)
03

#5450000
1!
1)
b100001001 /
13

#5460000
0!
0)
03

#5470000
1!
1)
b100001010 /
13

#5480000
0!
0)
03

#5490000
1!
1)
b100001011 /
13

#5500000
0!
0)
03

#5510000
1!
1)
b100001100 /
13

#5520000
0!
0)
03

#5530000
1!
1)
b100001101 /
13

#5540000
0!
0)
03

#5550000
1!
1)
b100001110 /
13

#5560000
0!
0)
03

#5570000
1!
1)
b100001111 /
13

#5580000
0!
0)
03

#5590000
1!
1)
b100010000 /
13

#5600000
0!
0)
03

#5610000
1!
1)
b100010001 /
13

#5620000
0!
0)
03

#5630000
1!
1)
b100010010 /
13

#5640000
0!
0)
03

#5650000
1!
1)
b100010011 /
13

#5660000
0!
0)
03

#5670000
1!
1)
b100010100 /
13

#5680000
0!
0)
03

#5690000
1!
1)
b100010101 /
13

#5700000
0!
0)
03

#5710000
1!
1)
b100010110 /
13

#5720000
0!
0)
03

#5730000
1!
1)
b100010111 /
13

#5740000
0!
0)
03

#5750000
1!
1)
b100011000 /
13

#5760000
0!
0)
03

#5770000
1!
1)
b100011001 /
13

#5780000
0!
0)
03

#5790000
1!
1)
b100011010 /
13

#5800000
0!
0)
03

#5810000
1!
1)
b100011011 /
13

#5820000
0!
0)
03

#5830000
1!
1)
b100011100 /
13

#5840000
0!
0)
03

#5850000
1!
1)
b100011101 /
13

#5860000
0!
0)
03

#5870000
1!
1)
b100011110 /
13

#5880000
0!
0)
03

#5890000
1!
1)
b100011111 /
13

#5900000
0!
0)
03

#5910000
1!
1)
b100100000 /
13

#5920000
0!
0)
03

#5930000
1!
1)
b100100001 /
13

#5940000
0!
0)
03

#5950000
1!
1)
b100100010 /
13

#5960000
0!
0)
03

#5970000
1!
1)
b100100011 /
13

#5980000
0!
0)
03

#5990000
1!
1)
b100100100 /
13

#6000000
0!
0)
03

#6010000
1!
1)
b100100101 /
13

#6020000
0!
0)
03

#6030000
1!
1)
b100100110 /
13

#6040000
0!
0)
03

#6050000
1!
1)
b100100111 /
13

#6060000
0!
0)
03

#6070000
1!
1)
b100101000 /
13

#6080000
0!
0)
03

#6090000
1!
1)
b100101001 /
13

#6100000
0!
0)
03

#6110000
1!
1)
b100101010 /
13

#6120000
0!
0)
03

#6130000
1!
1)
b100101011 /
13

#6140000
0!
0)
03

#6150000
1!
1)
b100101100 /
13

#6160000
0!
0)
03

#6170000
1!
1)
b100101101 /
13

#6180000
0!
0)
03

#6190000
1!
1)
b100101110 /
13

#6200000
0!
0)
03

#6210000
1!
1)
b100101111 /
13

#6220000
0!
0)
03

#6230000
1!
1)
b100110000 /
13

#6240000
0!
0)
03

#6250000
1!
1)
b100110001 /
13

#6260000
0!
0)
03

#6270000
1!
1)
b100110010 /
13

#6280000
0!
0)
03

#6290000
1!
1)
b100110011 /
13

#6300000
0!
0)
03

#6310000
1!
1)
b100110100 /
13

#6320000
0!
0)
03

#6330000
1!
1)
b100110101 /
13

#6340000
0!
0)
03

#6350000
1!
1)
b100110110 /
13

#6360000
0!
0)
03

#6370000
1!
1)
b100110111 /
13

#6380000
0!
0)
03

#6390000
1!
1)
b100111000 /
13

#6400000
0!
0)
03

#6410000
1!
1)
b100111001 /
13

#6420000
0!
0)
03

#6430000
1!
1)
b100111010 /
13

#6440000
0!
0)
03

#6450000
1!
1)
b100111011 /
13

#6460000
0!
0)
03

#6470000
1!
1)
b100111100 /
13

#6480000
0!
0)
03

#6490000
1!
1)
b100111101 /
13

#6500000
0!
0)
03

#6510000
1!
1)
b100111110 /
13

#6520000
0!
0)
03

#6530000
1!
1)
b100111111 /
13

#6540000
0!
0)
03

#6550000
1!
1)
b101000000 /
13

#6560000
0!
0)
03

#6570000
1!
1)
b101000001 /
13

#6580000
0!
0)
03

#6590000
1!
1)
b101000010 /
13

#6600000
0!
0)
03

#6610000
1!
1)
b101000011 /
13

#6620000
0!
0)
03

#6630000
1!
1)
b101000100 /
13

#6640000
0!
0)
03

#6650000
1!
1)
b101000101 /
13

#6660000
0!
0)
03

#6670000
1!
1)
b101000110 /
13

#6680000
0!
0)
03

#6690000
1!
1)
b101000111 /
13

#6700000
0!
0)
03

#6710000
1!
1)
b101001000 /
13

#6720000
0!
0)
03

#6730000
1!
1)
b101001001 /
13

#6740000
0!
0)
03

#6750000
1!
1)
b101001010 /
13

#6760000
0!
0)
03

#6770000
1!
1)
b101001011 /
13

#6780000
0!
0)
03

#6790000
1!
1)
b101001100 /
13

#6800000
0!
0)
03

#6810000
1!
1)
b101001101 /
13

#6820000
0!
0)
03

#6830000
1!
1)
b101001110 /
13

#6840000
0!
0)
03

#6850000
1!
1)
b101001111 /
13

#6860000
0!
0)
03

#6870000
1!
1)
b101010000 /
13

#6880000
0!
0)
03

#6890000
1!
1)
b101010001 /
13

#6900000
0!
0)
03

#6910000
1!
1)
b101010010 /
13

#6920000
0!
0)
03

#6930000
1!
1)
b101010011 /
13

#6940000
0!
0)
03

#6950000
1!
1)
b101010100 /
13

#6960000
0!
0)
03

#6970000
1!
1)
b101010101 /
13

#6980000
0!
0)
03

#6990000
1!
1)
b101010110 /
13

#7000000
0!
0)
03

#7010000
1!
1)
b101010111 /
13

#7020000
0!
0)
03

#7030000
1!
1)
b101011000 /
13

#7040000
0!
0)
03

#7050000
1!
1)
b101011001 /
13

#7060000
0!
0)
03

#7070000
1!
1)
b101011010 /
13

#7080000
0!
0)
03

#7090000
1!
1)
b101011011 /
13

#7100000
0!
0)
03

#7110000
1!
1)
b101011100 /
13

#7120000
0!
0)
03

#7130000
1!
1)
b101011101 /
13

#7140000
0!
0)
03

#7150000
1!
1)
b101011110 /
13

#7160000
0!
0)
03

#7170000
1!
1)
b101011111 /
13

#7180000
0!
0)
03

#7190000
1!
1)
b101100000 /
13

#7200000
0!
0)
03

#7210000
1!
1)
b101100001 /
13

#7220000
0!
0)
03

#7230000
1!
1)
b101100010 /
13

#7240000
0!
0)
03

#7250000
1!
1)
b101100011 /
13

#7260000
0!
0)
03

#7270000
1!
1)
b101100100 /
13

#7280000
0!
0)
03

#7290000
1!
1)
b101100101 /
13

#7300000
0!
0)
03

#7310000
1!
1)
b101100110 /
13

#7320000
0!
0)
03

#7330000
1!
1)
b101100111 /
13

#7340000
0!
0)
03

#7350000
1!
1)
b101101000 /
13

#7360000
0!
0)
03

#7370000
1!
1)
b101101001 /
13

#7380000
0!
0)
03

#7390000
1!
1)
b101101010 /
13

#7400000
0!
0)
03

